{
	"name": "Game",
	"layers": [
		{
			"name": "Game",
			"overriden": 0,
			"subLayers": [
				{
					"name": "Background",
					"overriden": 0,
					"subLayers": [],
					"instances": [
						{
							"type": "DirtTerrainBackground",
							"properties": {
								"initially-visible": true,
								"origin": "top-left",
								"wrap-horizontal": "repeat",
								"wrap-vertical": "repeat",
								"image-offset-x": 0,
								"image-offset-y": 0,
								"image-scale-x": 1,
								"image-scale-y": 1,
								"image-angle": 0
							},
							"uid": 5,
							"instanceVariables": {},
							"behaviors": {},
							"world": {
								"x": 0,
								"y": 0,
								"width": 3840,
								"height": 2160,
								"originX": 0,
								"originY": 0,
								"color": [
									1,
									1,
									1,
									1
								],
								"angle": 0,
								"zElevation": 0
							}
						}
					],
					"sid": 998376288250594,
					"effectTypes": [],
					"isInitiallyVisible": true,
					"isInitiallyInteractive": true,
					"color": [
						1,
						1,
						1,
						1
					],
					"backgroundColor": [
						1,
						1,
						1,
						1
					],
					"isTransparent": false,
					"parallaxX": 1,
					"parallaxY": 1,
					"scaleRate": 1,
					"forceOwnTexture": false,
					"renderingMode": "3d",
					"drawOrder": "z-order",
					"useRenderCells": false,
					"blendMode": "normal",
					"zElevation": 0,
					"global": false
				},
				{
					"name": "SelectionBoxes",
					"overriden": 0,
					"subLayers": [],
					"instances": [],
					"sid": 678377480080548,
					"effectTypes": [],
					"isInitiallyVisible": true,
					"isInitiallyInteractive": true,
					"color": [
						1,
						1,
						1,
						1
					],
					"backgroundColor": [
						0.23921568627450981,
						0.23921568627450981,
						0.23921568627450981,
						1
					],
					"isTransparent": true,
					"parallaxX": 1,
					"parallaxY": 1,
					"scaleRate": 1,
					"forceOwnTexture": false,
					"renderingMode": "3d",
					"drawOrder": "z-order",
					"useRenderCells": false,
					"blendMode": "normal",
					"zElevation": 0,
					"global": false
				},
				{
					"name": "UnitPlatforms",
					"overriden": 0,
					"subLayers": [],
					"instances": [],
					"sid": 133107057470987,
					"effectTypes": [],
					"isInitiallyVisible": true,
					"isInitiallyInteractive": true,
					"color": [
						1,
						1,
						1,
						1
					],
					"backgroundColor": [
						0.7607843137254902,
						0.7607843137254902,
						0.7607843137254902,
						1
					],
					"isTransparent": true,
					"parallaxX": 1,
					"parallaxY": 1,
					"scaleRate": 1,
					"forceOwnTexture": false,
					"renderingMode": "3d",
					"drawOrder": "z-order",
					"useRenderCells": false,
					"blendMode": "normal",
					"zElevation": 0,
					"global": false
				},
				{
					"name": "UnitTurrets",
					"overriden": 0,
					"subLayers": [],
					"instances": [
						{
							"type": "TankPlatform",
							"properties": {
								"initially-visible": true,
								"initial-animation": "Animation 1",
								"initial-frame": 0,
								"enable-collisions": true,
								"live-preview": false
							},
							"uid": 25,
							"instanceVariables": {},
							"behaviors": {},
							"world": {
								"x": 139,
								"y": -91,
								"width": 241,
								"height": 129,
								"originX": 0.5,
								"originY": 0.5,
								"color": [
									1,
									1,
									1,
									1
								],
								"angle": 0,
								"zElevation": 0
							}
						},
						{
							"type": "TankTurret",
							"properties": {
								"initially-visible": true,
								"initial-animation": "Animation 1",
								"initial-frame": 0,
								"enable-collisions": true,
								"live-preview": false
							},
							"uid": 27,
							"instanceVariables": {},
							"behaviors": {},
							"world": {
								"x": 123,
								"y": -88,
								"width": 190,
								"height": 95,
								"originX": 0.2631578947368421,
								"originY": 0.5157894736842106,
								"color": [
									1,
									1,
									1,
									1
								],
								"angle": 0,
								"zElevation": 0
							}
						}
					],
					"sid": 551716547056907,
					"effectTypes": [],
					"isInitiallyVisible": true,
					"isInitiallyInteractive": true,
					"color": [
						1,
						1,
						1,
						1
					],
					"backgroundColor": [
						1,
						1,
						1,
						1
					],
					"isTransparent": true,
					"parallaxX": 1,
					"parallaxY": 1,
					"scaleRate": 1,
					"forceOwnTexture": false,
					"renderingMode": "3d",
					"drawOrder": "z-order",
					"useRenderCells": false,
					"blendMode": "normal",
					"zElevation": 0,
					"global": false
				},
				{
					"name": "Projectiles",
					"overriden": 0,
					"subLayers": [],
					"instances": [
						{
							"type": "Explosion",
							"properties": {
								"initially-visible": true,
								"initial-animation": "Default",
								"initial-frame": 0,
								"enable-collisions": true,
								"live-preview": false
							},
							"uid": 26,
							"instanceVariables": {},
							"behaviors": {
								"Fade": {
									"properties": {
										"fade-in-time": 0,
										"wait-time": 0,
										"fade-out-time": 0.5,
										"destroy": true,
										"enabled": true,
										"live-preview": false
									}
								}
							},
							"world": {
								"x": 430,
								"y": -169,
								"width": 185.1853232856104,
								"height": 158.5060817953106,
								"originX": 0.5,
								"originY": 0.504951,
								"color": [
									1,
									1,
									1,
									1
								],
								"angle": 0,
								"zElevation": 0,
								"blendMode": "additive"
							}
						}
					],
					"sid": 448510668994478,
					"effectTypes": [],
					"isInitiallyVisible": true,
					"isInitiallyInteractive": true,
					"color": [
						1,
						1,
						1,
						1
					],
					"backgroundColor": [
						1,
						1,
						1,
						1
					],
					"isTransparent": true,
					"parallaxX": 1,
					"parallaxY": 1,
					"scaleRate": 1,
					"forceOwnTexture": false,
					"renderingMode": "3d",
					"drawOrder": "z-order",
					"useRenderCells": false,
					"blendMode": "normal",
					"zElevation": 0,
					"global": false
				},
				{
					"name": "Explosions",
					"overriden": 0,
					"subLayers": [],
					"instances": [],
					"sid": 654108764822993,
					"effectTypes": [],
					"isInitiallyVisible": true,
					"isInitiallyInteractive": true,
					"color": [
						1,
						1,
						1,
						1
					],
					"backgroundColor": [
						1,
						1,
						1,
						1
					],
					"isTransparent": true,
					"parallaxX": 1,
					"parallaxY": 1,
					"scaleRate": 1,
					"forceOwnTexture": false,
					"renderingMode": "3d",
					"drawOrder": "z-order",
					"useRenderCells": false,
					"blendMode": "normal",
					"zElevation": 0,
					"global": false
				}
			],
			"instances": [],
			"sid": 442148768824181,
			"effectTypes": [],
			"isInitiallyVisible": true,
			"isInitiallyInteractive": true,
			"color": [
				1,
				1,
				1,
				1
			],
			"backgroundColor": [
				1,
				1,
				1,
				1
			],
			"isTransparent": true,
			"parallaxX": 1,
			"parallaxY": 1,
			"scaleRate": 1,
			"forceOwnTexture": false,
			"renderingMode": "3d",
			"drawOrder": "z-order",
			"useRenderCells": false,
			"blendMode": "normal",
			"zElevation": 0,
			"global": false
		},
		{
			"name": "Interface",
			"overriden": 0,
			"subLayers": [
				{
					"name": "DragSelectionBox",
					"overriden": 0,
					"subLayers": [],
					"instances": [],
					"sid": 593658404322465,
					"effectTypes": [],
					"isInitiallyVisible": true,
					"isInitiallyInteractive": true,
					"color": [
						1,
						1,
						1,
						1
					],
					"backgroundColor": [
						1,
						1,
						1,
						1
					],
					"isTransparent": true,
					"parallaxX": 0,
					"parallaxY": 0,
					"scaleRate": 1,
					"forceOwnTexture": false,
					"renderingMode": "2d",
					"drawOrder": "z-order",
					"useRenderCells": false,
					"blendMode": "normal",
					"zElevation": 0,
					"global": false
				},
				{
					"name": "UI",
					"overriden": 0,
					"subLayers": [],
					"instances": [
						{
							"type": "MinimapCanvas",
							"properties": {
								"resolution-mode": "auto",
								"initially-visible": true,
								"origin": "top-left",
								"antialiasing": "off"
							},
							"uid": 32,
							"instanceVariables": {},
							"behaviors": {},
							"world": {
								"x": 0,
								"y": 0,
								"width": 200,
								"height": 200,
								"originX": 0,
								"originY": 0,
								"color": [
									1,
									1,
									1,
									1
								],
								"angle": 0
							}
						},
						{
							"type": "StatsText",
							"properties": {
								"text": "Stats...",
								"enable-bbcode": true,
								"font": "Arial",
								"size": 12,
								"line-height": 0,
								"bold": false,
								"italic": false,
								"color": [
									1,
									1,
									1,
									1
								],
								"horizontal-alignment": "left",
								"vertical-alignment": "bottom",
								"wrapping": "word",
								"initially-visible": true,
								"origin": "top-left"
							},
							"uid": 33,
							"instanceVariables": {},
							"behaviors": {},
							"world": {
								"x": 3,
								"y": 811,
								"width": 434,
								"height": 265,
								"originX": 0,
								"originY": 0,
								"color": [
									1,
									1,
									1,
									1
								],
								"angle": 0,
								"zElevation": 0
							}
						}
					],
					"sid": 486341906092172,
					"effectTypes": [],
					"isInitiallyVisible": true,
					"isInitiallyInteractive": true,
					"color": [
						1,
						1,
						1,
						1
					],
					"backgroundColor": [
						1,
						1,
						1,
						1
					],
					"isTransparent": true,
					"parallaxX": 0,
					"parallaxY": 0,
					"scaleRate": 1,
					"forceOwnTexture": false,
					"renderingMode": "2d",
					"drawOrder": "z-order",
					"useRenderCells": false,
					"blendMode": "normal",
					"zElevation": 0,
					"global": false
				}
			],
			"instances": [],
			"sid": 206558111644816,
			"effectTypes": [],
			"isInitiallyVisible": true,
			"isInitiallyInteractive": true,
			"color": [
				1,
				1,
				1,
				1
			],
			"backgroundColor": [
				1,
				1,
				1,
				1
			],
			"isTransparent": true,
			"parallaxX": 1,
			"parallaxY": 1,
			"scaleRate": 1,
			"forceOwnTexture": false,
			"renderingMode": "2d",
			"drawOrder": "z-order",
			"useRenderCells": false,
			"blendMode": "normal",
			"zElevation": 0,
			"global": false
		}
	],
	"sid": 998293964461738,
	"nonworld-instances": [],
	"effectTypes": [],
	"width": 3840,
	"height": 2160,
	"unboundedScrolling": true,
	"vpX": 0.5,
	"vpY": 0.5,
	"projection": "perspective",
	"eventSheet": null
}